bech32m/__init__.py
bech32m/codecs.py
bech32m-1.0.0.dist-info/METADATA
bech32m-1.0.0.dist-info/WHEEL
bech32m-1.0.0.dist-info/licenses/LICENSE
bech32m-1.0.0.dist-info/RECORD
