Metadata-Version: 2.1
Name: bech32m
Version: 1.0.0
Summary: Encoding/decoding Bech32 and Bech32m
Project-URL: Source, https://github.com/ods/bech32m
Author-email: Denis Otkidach <denis.otkidach@gmail.com>
License-Expression: MIT
License-File: LICENSE
Keywords: bech32,bech32m,bitcoin,blockchain
Classifier: Development Status :: 5 - Production/Stable
Classifier: License :: OSI Approved :: MIT License
Classifier: Programming Language :: Python
Classifier: Programming Language :: Python :: 3.9
Classifier: Programming Language :: Python :: 3.10
Classifier: Programming Language :: Python :: 3.11
Classifier: Topic :: Security :: Cryptography
Requires-Python: >=3.9
